<?xml version='1.0' encoding='UTF-8' ?>
<MILSEARCH><RESULT><TITLE><![CDATA[河北军民融合暨<font color=rEd>国防工业</font>协同创新成果展览洽谈会召开
]]></TITLE><CONTENT><![CDATA[]]></CONTENT><AUTHOR><![CDATA[李鸥、翼飞、兵者]]></AUTHOR><URL><![CDATA[http://www.mod.gov.cn/video/2015-12/06/content_4631922.htm]]></URL><SOURCE><![CDATA[国防部网]]></SOURCE><CLASS1><![CDATA[国防视频]]></CLASS1><CLASS2><![CDATA[新闻视听]]></CLASS2><KEYWORD><![CDATA[军民融合]]></KEYWORD><IMAGE><![CDATA[http://img.mod.gov.cn/video/attachement/jpg/site21/20151208/1517ee3ff4246319222611.jpg]]></IMAGE><DOCTYPE><![CDATA[1]]></DOCTYPE><LANGUAGES><![CDATA[1]]></LANGUAGES><SITENAME><![CDATA[国防部中文版]]></SITENAME><MASTER><![CDATA[0]]></MASTER><TRSID><![CDATA[057B52972.0000CAF2.4944]]></TRSID><INPUTTIME><![CDATA[2015.12.8.]]></INPUTTIME><PUBLISHTIME><![CDATA[2015.12.6]]></PUBLISHTIME><RELEVANCE><![CDATA[0.0]]></RELEVANCE></RESULT><RESULT><TITLE><![CDATA[河北军民融合暨<font color=rEd>国防工业</font>协同创新成果展览洽谈会召开
]]></TITLE><CONTENT><![CDATA[]]></CONTENT><AUTHOR><![CDATA[李鸥、翼飞、兵者]]></AUTHOR><URL><![CDATA[http://www.mod.gov.cn/video/2015-12/06/content_4631919.htm]]></URL><SOURCE><![CDATA[国防部网]]></SOURCE><CLASS1><![CDATA[国防视频]]></CLASS1><CLASS2><![CDATA[新闻视听]]></CLASS2><KEYWORD><![CDATA[军民融合]]></KEYWORD><IMAGE><![CDATA[http://img.mod.gov.cn/video/attachement/jpg/site21/20151208/4437e658885f17d0629a01.jpg]]></IMAGE><DOCTYPE><![CDATA[1]]></DOCTYPE><LANGUAGES><![CDATA[1]]></LANGUAGES><SITENAME><![CDATA[国防部中文版]]></SITENAME><MASTER><![CDATA[0]]></MASTER><TRSID><![CDATA[057B52972.0000C754.6400]]></TRSID><INPUTTIME><![CDATA[2015.12.8.]]></INPUTTIME><PUBLISHTIME><![CDATA[2015.12.6]]></PUBLISHTIME><RELEVANCE><![CDATA[0.0]]></RELEVANCE></RESULT><RESULT><TITLE><![CDATA[直击军民融合暨<font color=rEd>国防工业</font>协同创新成果展：无人机、气垫船齐亮相！
]]></TITLE><CONTENT><![CDATA[]]></CONTENT><AUTHOR><![CDATA[李鸥、兵者]]></AUTHOR><URL><![CDATA[http://www.mod.gov.cn/hdpic/2015-12/06/content_4631787.htm]]></URL><SOURCE><![CDATA[国防部网]]></SOURCE><CLASS1><![CDATA[首页热图]]></CLASS1><CLASS2><![CDATA[高清大图]]></CLASS2><KEYWORD><![CDATA[军民融合,无人机,气垫船]]></KEYWORD><IMAGE><![CDATA[http://img.mod.gov.cn/hdpic/attachement/jpg/site21/20151206/15176f0fa2246317878691.jpg]]></IMAGE><DOCTYPE><![CDATA[2]]></DOCTYPE><LANGUAGES><![CDATA[1]]></LANGUAGES><SITENAME><![CDATA[国防部中文版]]></SITENAME><MASTER><![CDATA[0]]></MASTER><TRSID><![CDATA[057B52972.0000C6D8.E0E2]]></TRSID><INPUTTIME><![CDATA[2015.12.6.]]></INPUTTIME><PUBLISHTIME><![CDATA[2015.12.6]]></PUBLISHTIME><RELEVANCE><![CDATA[0.0]]></RELEVANCE></RESULT><RESULT><TITLE><![CDATA[印度发布国家计划提高<font color=rEd>国防工业</font>能力
]]></TITLE><CONTENT><![CDATA[&nbsp;&nbsp;&nbsp;&nbsp;&nbsp;&nbsp;&nbsp;&nbsp;[根据简氏新闻网2015年7月9日报道]印度工业联合会(CII)2015年7月8日宣布一项国家计划，致力于提高能力支持国防产业的发展。计划中，战略制造技能委员会(SMSC)将为全国各地的年轻人提供国防生产相关技能、造船]]></CONTENT><AUTHOR><![CDATA[朱佳文]]></AUTHOR><URL><![CDATA[http://www.mod.gov.cn/wqzb/2015-07/14/content_4594976.htm]]></URL><SOURCE><![CDATA[国防科技信息网]]></SOURCE><CLASS1><![CDATA[武器装备]]></CLASS1><CLASS2><![CDATA[2016年改版前国防部网站]]></CLASS2><KEYWORD><![CDATA[]]></KEYWORD><IMAGE><![CDATA[]]></IMAGE><DOCTYPE><![CDATA[1]]></DOCTYPE><LANGUAGES><![CDATA[1]]></LANGUAGES><SITENAME><![CDATA[国防部中文版]]></SITENAME><MASTER><![CDATA[0]]></MASTER><TRSID><![CDATA[057B525CA.00006408.5DF6]]></TRSID><INPUTTIME><![CDATA[2015.7.14.]]></INPUTTIME><PUBLISHTIME><![CDATA[2015.7.14]]></PUBLISHTIME><RELEVANCE><![CDATA[0.0]]></RELEVANCE></RESULT><RESULT><TITLE><![CDATA[毛泽东布局新中国<font color=rEd>国防工业</font>
]]></TITLE><CONTENT><![CDATA[
1952年2月，毛泽东视察南昌舰
新中国建立伊始，面对复杂的国内外形势，为保卫领土完整，维护民族尊严，提高国际地位，毛泽东下定决心，必须建设强大的国防和为之服务的现代国防工业。
1949年9月21日，第一届政协会议]]></CONTENT><AUTHOR><![CDATA[袁和平]]></AUTHOR><URL><![CDATA[http://www.mod.gov.cn/hist/2014-10/27/content_4558963.htm]]></URL><SOURCE><![CDATA[军工文化]]></SOURCE><CLASS1><![CDATA[军事历史]]></CLASS1><CLASS2><![CDATA[军事技术史]]></CLASS2><KEYWORD><![CDATA[国防工业,新中国国防工业,毛泽东,国防,武器装备,万国牌,军工,陆军武器,弹药,空军,海军,兵工,航空,电信,船舶工业,陆军装备,火炮,坦克,水雷,歼7,导弹潜艇]]></KEYWORD><IMAGE><![CDATA[http://img.mod.gov.cn/hist/attachement/jpg/site21/20141027/14a5c5631ca45589639894.jpg]]></IMAGE><DOCTYPE><![CDATA[2]]></DOCTYPE><LANGUAGES><![CDATA[1]]></LANGUAGES><SITENAME><![CDATA[国防部中文版]]></SITENAME><MASTER><![CDATA[0]]></MASTER><TRSID><![CDATA[057B521EC.000003B2.6A7E]]></TRSID><INPUTTIME><![CDATA[2014.12.18.]]></INPUTTIME><PUBLISHTIME><![CDATA[2014.10.27]]></PUBLISHTIME><RELEVANCE><![CDATA[0.0]]></RELEVANCE></RESULT><RESULT><TITLE><![CDATA[军事现代化项目将促进世界<font color=rEd>国防工业</font>的发展
]]></TITLE><CONTENT><![CDATA[　　[据航宇防务网2014年8月20日报道] 最近Frost＆Sullivan公司选定10个国家对其国防预算进行了分析，包括：阿尔及利亚、巴西、智利、印度、印度尼西亚、日本、阿曼、波兰、俄罗斯和阿联酋，并发布了题为《快速发展的]]></CONTENT><AUTHOR><![CDATA[余静]]></AUTHOR><URL><![CDATA[http://www.mod.gov.cn/mobilize/2014-08/21/content_4531091.htm]]></URL><SOURCE><![CDATA[国防科技信息网]]></SOURCE><CLASS1><![CDATA[国防动员]]></CLASS1><CLASS2><![CDATA[2016年改版前国防部网站]]></CLASS2><KEYWORD><![CDATA[]]></KEYWORD><IMAGE><![CDATA[]]></IMAGE><DOCTYPE><![CDATA[1]]></DOCTYPE><LANGUAGES><![CDATA[1]]></LANGUAGES><SITENAME><![CDATA[国防部中文版]]></SITENAME><MASTER><![CDATA[0]]></MASTER><TRSID><![CDATA[057B53056.00018342.DF13]]></TRSID><INPUTTIME><![CDATA[2014.8.21.]]></INPUTTIME><PUBLISHTIME><![CDATA[2014.8.21]]></PUBLISHTIME><RELEVANCE><![CDATA[0.0]]></RELEVANCE></RESULT><RESULT><TITLE><![CDATA[军事现代化项目将促进世界<font color=rEd>国防工业</font>的发展
]]></TITLE><CONTENT><![CDATA[　　[据航宇防务网2014年8月20日报道] 最近Frost＆Sullivan公司选定10个国家对其国防预算进行了分析，包括：阿尔及利亚、巴西、智利、印度、印度尼西亚、日本、阿曼、波兰、俄罗斯和阿联酋，并发布了题为《快速发展的]]></CONTENT><AUTHOR><![CDATA[余静]]></AUTHOR><URL><![CDATA[http://www.mod.gov.cn/wqzb/2014-08/21/content_4531080.htm]]></URL><SOURCE><![CDATA[国防科技信息网]]></SOURCE><CLASS1><![CDATA[武器装备]]></CLASS1><CLASS2><![CDATA[2016年改版前国防部网站]]></CLASS2><KEYWORD><![CDATA[]]></KEYWORD><IMAGE><![CDATA[]]></IMAGE><DOCTYPE><![CDATA[1]]></DOCTYPE><LANGUAGES><![CDATA[1]]></LANGUAGES><SITENAME><![CDATA[国防部中文版]]></SITENAME><MASTER><![CDATA[0]]></MASTER><TRSID><![CDATA[057B53055.0001746C.97F0]]></TRSID><INPUTTIME><![CDATA[2014.8.21.]]></INPUTTIME><PUBLISHTIME><![CDATA[2014.8.21]]></PUBLISHTIME><RELEVANCE><![CDATA[0.0]]></RELEVANCE></RESULT><RESULT><TITLE><![CDATA[印度<font color=rEd>国防工业</font>“空心化” 军购买不来军事强国
]]></TITLE><CONTENT><![CDATA[&nbsp;&nbsp;&nbsp;&nbsp;&nbsp;&nbsp;&nbsp;&nbsp;通过军购，印度国防工业发展取得了令人瞩目的成就，但风光背后隐藏着其民族国防工业“空心化”的隐患——
&nbsp;&nbsp;&nbsp;&nbsp;&nbsp;&nbsp;&nbsp;&nbsp;“拿来主义”成就不了军事强国
&nbsp;&nbsp;&nbsp;&nbsp;&nbsp;&nbsp;&nbsp;&nbsp;印度国防工业本土化和自主化不足的现状，似乎已招致]]></CONTENT><AUTHOR><![CDATA[温振华]]></AUTHOR><URL><![CDATA[http://www.mod.gov.cn/opinion/2014-06/10/content_4515200.htm]]></URL><SOURCE><![CDATA[解放军报]]></SOURCE><CLASS1><![CDATA[防务观察]]></CLASS1><CLASS2><![CDATA[2016年改版前国防部网站]]></CLASS2><KEYWORD><![CDATA[印度 国防工业 “空心化”]]></KEYWORD><IMAGE><![CDATA[]]></IMAGE><DOCTYPE><![CDATA[1]]></DOCTYPE><LANGUAGES><![CDATA[1]]></LANGUAGES><SITENAME><![CDATA[国防部中文版]]></SITENAME><MASTER><![CDATA[0]]></MASTER><TRSID><![CDATA[057B52D30.000135AF.B196]]></TRSID><INPUTTIME><![CDATA[2014.6.10.]]></INPUTTIME><PUBLISHTIME><![CDATA[2014.6.10]]></PUBLISHTIME><RELEVANCE><![CDATA[0.0]]></RELEVANCE></RESULT><RESULT><TITLE><![CDATA[印度<font color=rEd>国防工业</font>“空心化” 军购买不来军事强国
]]></TITLE><CONTENT><![CDATA[&nbsp;&nbsp;&nbsp;&nbsp;&nbsp;&nbsp;&nbsp;&nbsp;通过军购，印度国防工业发展取得了令人瞩目的成就，但风光背后隐藏着其民族国防工业“空心化”的隐患——
&nbsp;&nbsp;&nbsp;&nbsp;&nbsp;&nbsp;&nbsp;&nbsp;“拿来主义”成就不了军事强国
&nbsp;&nbsp;&nbsp;&nbsp;&nbsp;&nbsp;&nbsp;&nbsp;印度国防工业本土化和自主化不足的现状，似乎已招致]]></CONTENT><AUTHOR><![CDATA[温振华]]></AUTHOR><URL><![CDATA[http://wap.mod.gov.cn/h/fw/2014-06/10/content_4515191.htm]]></URL><SOURCE><![CDATA[解放军报]]></SOURCE><CLASS1><![CDATA[手机国防部网]]></CLASS1><CLASS2><![CDATA[防务视点]]></CLASS2><KEYWORD><![CDATA[印度 国防工业 “空心化” 军购 军事强国]]></KEYWORD><IMAGE><![CDATA[]]></IMAGE><DOCTYPE><![CDATA[1]]></DOCTYPE><LANGUAGES><![CDATA[1]]></LANGUAGES><SITENAME><![CDATA[手机国防部网]]></SITENAME><MASTER><![CDATA[0]]></MASTER><TRSID><![CDATA[057B52DDE.0001452E.0F0D]]></TRSID><INPUTTIME><![CDATA[2014.6.10.]]></INPUTTIME><PUBLISHTIME><![CDATA[2014.6.10]]></PUBLISHTIME><RELEVANCE><![CDATA[0.0]]></RELEVANCE></RESULT><RESULT><TITLE><![CDATA[“信息集成”为<font color=rEd>国防工业</font>注入新活力
]]></TITLE><CONTENT><![CDATA[　　为期3天的第九届中国国际国防电子展今日在中国国际展览中心落下帷幕。展会上，中国军工企业展出了多款最新型的电子产品，新型海上作战指挥系统、近程防空作战系统、反隐身雷达、新型无人机等装备一一亮相。
　　]]></CONTENT><AUTHOR><![CDATA[贾玉省　徐　琳]]></AUTHOR><URL><![CDATA[http://wap.mod.gov.cn/h/fw/2014-05/11/content_4508084.htm]]></URL><SOURCE><![CDATA[解放军报]]></SOURCE><CLASS1><![CDATA[手机国防部网]]></CLASS1><CLASS2><![CDATA[防务视点]]></CLASS2><KEYWORD><![CDATA[]]></KEYWORD><IMAGE><![CDATA[]]></IMAGE><DOCTYPE><![CDATA[1]]></DOCTYPE><LANGUAGES><![CDATA[1]]></LANGUAGES><SITENAME><![CDATA[手机国防部网]]></SITENAME><MASTER><![CDATA[0]]></MASTER><TRSID><![CDATA[057B52EA1.0001544F.40D7]]></TRSID><INPUTTIME><![CDATA[2014.5.11.]]></INPUTTIME><PUBLISHTIME><![CDATA[2014.5.11]]></PUBLISHTIME><RELEVANCE><![CDATA[0.0]]></RELEVANCE></RESULT><NODESEARCHNAMEROOT><CLASSRES><CLASSVALUE><![CDATA[全部]]></CLASSVALUE><CLASSNUM><![CDATA[10]]></CLASSNUM></CLASSRES><CLASSRES><CLASSVALUE><![CDATA[武器装备]]></CLASSVALUE><CLASSNUM><![CDATA[2]]></CLASSNUM></CLASSRES><CLASSRES><CLASSVALUE><![CDATA[国防视频]]></CLASSVALUE><CLASSNUM><![CDATA[2]]></CLASSNUM></CLASSRES><CLASSRES><CLASSVALUE><![CDATA[视点]]></CLASSVALUE><CLASSNUM><![CDATA[1]]></CLASSNUM></CLASSRES><CLASSRES><CLASSVALUE><![CDATA[防务视点]]></CLASSVALUE><CLASSNUM><![CDATA[1]]></CLASSNUM></CLASSRES></NODESEARCHNAMEROOT><CURPAGE><![CDATA[1]]></CURPAGE><PAGES><![CDATA[1]]></PAGES><PAGECOUNT><![CDATA[9999]]></PAGECOUNT><TOTALCOUNT><![CDATA[10]]></TOTALCOUNT><SEARCHTIME><![CDATA[40]]></SEARCHTIME></MILSEARCH>

