<?xml version='1.0' encoding='UTF-8' ?>
<MILSEARCH><RESULT><TITLE><![CDATA[首届武器<font color=rEd>装备建设</font>军民融合式发展论坛举行
]]></TITLE><CONTENT><![CDATA[12月17日，由装备学院、国防科技信息研究中心、武器装备论证研究中心、国防工业出版社联合召开的首届“武器装备建设军民融合式发展论坛”在京举行。
论坛全面贯彻习主席军民融合深度发展的战略思想，深入推进装备建设]]></CONTENT><AUTHOR><![CDATA[邹维荣]]></AUTHOR><URL><![CDATA[http://www.mod.gov.cn/mobilization/2015-12/18/content_4642282.htm]]></URL><SOURCE><![CDATA[解放军报]]></SOURCE><CLASS1><![CDATA[国防部网]]></CLASS1><CLASS2><![CDATA[国防动员]]></CLASS2><KEYWORD><![CDATA[]]></KEYWORD><IMAGE><![CDATA[]]></IMAGE><DOCTYPE><![CDATA[1]]></DOCTYPE><LANGUAGES><![CDATA[1]]></LANGUAGES><SITENAME><![CDATA[国防部中文版]]></SITENAME><MASTER><![CDATA[0]]></MASTER><TRSID><![CDATA[057B52A36.0000E890.CF8A]]></TRSID><INPUTTIME><![CDATA[2016.2.18.]]></INPUTTIME><PUBLISHTIME><![CDATA[2015.12.18]]></PUBLISHTIME><RELEVANCE><![CDATA[0.0]]></RELEVANCE></RESULT><RESULT><TITLE><![CDATA[首届武器<font color=rEd>装备建设</font>军民融合发展论坛举行
]]></TITLE><CONTENT><![CDATA[元旦前夕，由装备学院、国防科技信息研究中心、武器装备论证研究中心、国防工业出版社联合召开的首届“武器装备建设军民融合发展论坛”在京举行。此次论坛，来自总部及军兵种装备机关人员、科研院所专家学者和企业代]]></CONTENT><AUTHOR><![CDATA[王瑶]]></AUTHOR><URL><![CDATA[http://www.mod.gov.cn/power/2016-01/04/content_4641856.htm]]></URL><SOURCE><![CDATA[中国国防报]]></SOURCE><CLASS1><![CDATA[国防部网]]></CLASS1><CLASS2><![CDATA[武装力量]]></CLASS2><KEYWORD><![CDATA[]]></KEYWORD><IMAGE><![CDATA[]]></IMAGE><DOCTYPE><![CDATA[1]]></DOCTYPE><LANGUAGES><![CDATA[1]]></LANGUAGES><SITENAME><![CDATA[国防部中文版]]></SITENAME><MASTER><![CDATA[0]]></MASTER><TRSID><![CDATA[057B52972.0000CDD9.68A7]]></TRSID><INPUTTIME><![CDATA[2016.2.17.]]></INPUTTIME><PUBLISHTIME><![CDATA[2016.1.4]]></PUBLISHTIME><RELEVANCE><![CDATA[0.0]]></RELEVANCE></RESULT><RESULT><TITLE><![CDATA[坚决贯彻习主席的<font color=rEd>装备建设</font>思想大力推进国防科技创新发展
]]></TITLE><CONTENT><![CDATA[&nbsp;&nbsp;&nbsp;&nbsp;&nbsp;&nbsp;&nbsp;&nbsp;本报北京6月22日电&nbsp;&nbsp;记者安普忠、倪大伟报道：中共中央政治局委员、中央军委副主席许其亮近日在江苏、上海、安徽等地调研时指出，习近平主席对加强新形势下我军武器装备建设作出一系列决策指示，为国防科技创]]></CONTENT><AUTHOR><![CDATA[安普忠、倪大伟]]></AUTHOR><URL><![CDATA[http://www.mod.gov.cn/auth/2015-06/23/content_4635716.htm]]></URL><SOURCE><![CDATA[解放军报]]></SOURCE><CLASS1><![CDATA[权威发布]]></CLASS1><CLASS2><![CDATA[重要信息]]></CLASS2><KEYWORD><![CDATA[]]></KEYWORD><IMAGE><![CDATA[]]></IMAGE><DOCTYPE><![CDATA[1]]></DOCTYPE><LANGUAGES><![CDATA[1]]></LANGUAGES><SITENAME><![CDATA[国防部中文版]]></SITENAME><MASTER><![CDATA[0]]></MASTER><TRSID><![CDATA[057B528BA.0000C239.A938]]></TRSID><INPUTTIME><![CDATA[2016.1.8.]]></INPUTTIME><PUBLISHTIME><![CDATA[2015.6.23]]></PUBLISHTIME><RELEVANCE><![CDATA[0.0]]></RELEVANCE></RESULT><RESULT><TITLE><![CDATA[首届武器<font color=rEd>装备建设</font>军民融合发展论坛举行
]]></TITLE><CONTENT><![CDATA[&nbsp;&nbsp;&nbsp;&nbsp;&nbsp;&nbsp;&nbsp;&nbsp;本报讯 记者王瑶报道：元旦前夕，由装备学院、国防科技信息研究中心、武器装备论证研究中心、国防工业出版社联合召开的首届“武器装备建设军民融合发展论坛”在京举行。此次论坛，来自总部及军兵种装备机关人]]></CONTENT><AUTHOR><![CDATA[记者王瑶]]></AUTHOR><URL><![CDATA[http://news.mod.gov.cn/militia/2016-01/04/content_4635159.htm]]></URL><SOURCE><![CDATA[中国国防报]]></SOURCE><CLASS1><![CDATA[中国民兵]]></CLASS1><CLASS2><![CDATA[2016年改版前国防部网站]]></CLASS2><KEYWORD><![CDATA[]]></KEYWORD><IMAGE><![CDATA[]]></IMAGE><DOCTYPE><![CDATA[1]]></DOCTYPE><LANGUAGES><![CDATA[1]]></LANGUAGES><SITENAME><![CDATA[国防部中文版]]></SITENAME><MASTER><![CDATA[0]]></MASTER><TRSID><![CDATA[057B52972.0000CC58.0C0E]]></TRSID><INPUTTIME><![CDATA[2016.1.4.]]></INPUTTIME><PUBLISHTIME><![CDATA[2016.1.4]]></PUBLISHTIME><RELEVANCE><![CDATA[0.0]]></RELEVANCE></RESULT><RESULT><TITLE><![CDATA[首届武器<font color=rEd>装备建设</font>军民融合式发展论坛举行
]]></TITLE><CONTENT><![CDATA[&nbsp;&nbsp;&nbsp;&nbsp;&nbsp;&nbsp;&nbsp;&nbsp;12月17日，由装备学院、国防科技信息研究中心、武器装备论证研究中心、国防工业出版社联合召开的首届“武器装备建设军民融合式发展论坛”在京举行。
&nbsp;&nbsp;&nbsp;&nbsp;&nbsp;&nbsp;&nbsp;&nbsp;论坛全面贯彻习主席军民融合深度发展的战略思想，]]></CONTENT><AUTHOR><![CDATA[邹维荣]]></AUTHOR><URL><![CDATA[http://www.mod.gov.cn/mobilize/2015-12/18/content_4633188.htm]]></URL><SOURCE><![CDATA[解放军报]]></SOURCE><CLASS1><![CDATA[国防动员]]></CLASS1><CLASS2><![CDATA[2016年改版前国防部网站]]></CLASS2><KEYWORD><![CDATA[]]></KEYWORD><IMAGE><![CDATA[]]></IMAGE><DOCTYPE><![CDATA[1]]></DOCTYPE><LANGUAGES><![CDATA[1]]></LANGUAGES><SITENAME><![CDATA[国防部中文版]]></SITENAME><MASTER><![CDATA[0]]></MASTER><TRSID><![CDATA[057B52973.0000D456.AE98]]></TRSID><INPUTTIME><![CDATA[2015.12.18.]]></INPUTTIME><PUBLISHTIME><![CDATA[2015.12.18]]></PUBLISHTIME><RELEVANCE><![CDATA[0.0]]></RELEVANCE></RESULT><RESULT><TITLE><![CDATA[首届“武器<font color=rEd>装备建设</font>军民融合式发展论坛”在北京举行
]]></TITLE><CONTENT><![CDATA[&nbsp;&nbsp;&nbsp;&nbsp;&nbsp;&nbsp;&nbsp;&nbsp;军报记者总装分社北京12月17日电（解放军报记者 邹维荣）12月17日，由装备学院、国防科技信息研究中心、武器装备论证研究中心、国防工业出版社联合召开的首届“武器装备建设军民融合式发展论坛”在京举行。
]]></CONTENT><AUTHOR><![CDATA[邹维荣]]></AUTHOR><URL><![CDATA[http://news.mod.gov.cn/headlines/2015-12/17/content_4633025.htm]]></URL><SOURCE><![CDATA[中国军网－军报记者]]></SOURCE><CLASS1><![CDATA[今日要闻]]></CLASS1><CLASS2><![CDATA[2016年改版前国防部网站]]></CLASS2><KEYWORD><![CDATA[]]></KEYWORD><IMAGE><![CDATA[http://img.mod.gov.cn/news/attachement/jpg/site21/20151217/4437e6581c3d17dcc22823.JPG]]></IMAGE><DOCTYPE><![CDATA[2]]></DOCTYPE><LANGUAGES><![CDATA[1]]></LANGUAGES><SITENAME><![CDATA[国防部中文版]]></SITENAME><MASTER><![CDATA[0]]></MASTER><TRSID><![CDATA[057B528B9.0000B42B.B6F2]]></TRSID><INPUTTIME><![CDATA[2015.12.17.]]></INPUTTIME><PUBLISHTIME><![CDATA[2015.12.17]]></PUBLISHTIME><RELEVANCE><![CDATA[0.0]]></RELEVANCE></RESULT><RESULT><TITLE><![CDATA[战场需求，<font color=rEd>装备建设</font>改革的直接牵引
]]></TITLE><CONTENT><![CDATA[&nbsp;&nbsp;&nbsp;&nbsp;&nbsp;&nbsp;&nbsp;&nbsp;恩格斯说：“暴力的胜利是以武器的生产为基础的。”武器装备是军队现代化程度的刚性标尺，也是打赢战争的重要物质基础。各军事大国在改革进程中，非常重视根据战争需求的变化，调整装备建设领导管理体制、创]]></CONTENT><AUTHOR><![CDATA[张　伶]]></AUTHOR><URL><![CDATA[http://www.mod.gov.cn/wqzb/2015-12/10/content_4632177.htm]]></URL><SOURCE><![CDATA[解放军报]]></SOURCE><CLASS1><![CDATA[武器装备]]></CLASS1><CLASS2><![CDATA[2016年改版前国防部网站]]></CLASS2><KEYWORD><![CDATA[]]></KEYWORD><IMAGE><![CDATA[]]></IMAGE><DOCTYPE><![CDATA[1]]></DOCTYPE><LANGUAGES><![CDATA[1]]></LANGUAGES><SITENAME><![CDATA[国防部中文版]]></SITENAME><MASTER><![CDATA[0]]></MASTER><TRSID><![CDATA[057B528B9.0000B944.0D44]]></TRSID><INPUTTIME><![CDATA[2015.12.10.]]></INPUTTIME><PUBLISHTIME><![CDATA[2015.12.10]]></PUBLISHTIME><RELEVANCE><![CDATA[0.0]]></RELEVANCE></RESULT><RESULT><TITLE><![CDATA[许其亮在苏沪皖调研<font color=rEd>装备建设</font>发展状况
]]></TITLE><CONTENT><![CDATA[]]></CONTENT><AUTHOR><![CDATA[黄显文、邬阳波等]]></AUTHOR><URL><![CDATA[http://www.mod.gov.cn/v/2015-06/23/content_4601193.htm]]></URL><SOURCE><![CDATA[CCTV]]></SOURCE><CLASS1><![CDATA[国防部网]]></CLASS1><CLASS2><![CDATA[视频]]></CLASS2><KEYWORD><![CDATA[许其亮]]></KEYWORD><IMAGE><![CDATA[http://www.mod.gov.cn/v/attachement/jpg/site21/20160201/4437e658885f1819018200.jpg]]></IMAGE><DOCTYPE><![CDATA[1]]></DOCTYPE><LANGUAGES><![CDATA[1]]></LANGUAGES><SITENAME><![CDATA[国防部中文版]]></SITENAME><MASTER><![CDATA[0]]></MASTER><TRSID><![CDATA[057B5273A.00008AF5.1E7B]]></TRSID><INPUTTIME><![CDATA[2015.7.20.]]></INPUTTIME><PUBLISHTIME><![CDATA[2015.6.23]]></PUBLISHTIME><RELEVANCE><![CDATA[0.0]]></RELEVANCE></RESULT><RESULT><TITLE><![CDATA[许其亮在苏沪皖调研<font color=rEd>装备建设</font>发展状况
]]></TITLE><CONTENT><![CDATA[]]></CONTENT><AUTHOR><![CDATA[黄显文、邬阳波等]]></AUTHOR><URL><![CDATA[http://www.mod.gov.cn/video/2015-06/23/content_4591329.htm]]></URL><SOURCE><![CDATA[CCTV]]></SOURCE><CLASS1><![CDATA[国防视频]]></CLASS1><CLASS2><![CDATA[2016年改版前国防部网站]]></CLASS2><KEYWORD><![CDATA[许其亮]]></KEYWORD><IMAGE><![CDATA[http://img.mod.gov.cn/video/attachement/jpg/site21/20150623/4437e658885f16f35b7501.jpg]]></IMAGE><DOCTYPE><![CDATA[1]]></DOCTYPE><LANGUAGES><![CDATA[1]]></LANGUAGES><SITENAME><![CDATA[国防部中文版]]></SITENAME><MASTER><![CDATA[0]]></MASTER><TRSID><![CDATA[057B525CC.00007461.9308]]></TRSID><INPUTTIME><![CDATA[2015.6.23.]]></INPUTTIME><PUBLISHTIME><![CDATA[2015.6.23]]></PUBLISHTIME><RELEVANCE><![CDATA[0.0]]></RELEVANCE></RESULT><RESULT><TITLE><![CDATA[坚决贯彻习主席的<font color=rEd>装备建设</font>思想大力推进国防科技创新发展
]]></TITLE><CONTENT><![CDATA[&nbsp;&nbsp;&nbsp;&nbsp;&nbsp;&nbsp;&nbsp;&nbsp;本报北京6月22日电&nbsp;&nbsp;记者安普忠、倪大伟报道：中共中央政治局委员、中央军委副主席许其亮近日在江苏、上海、安徽等地调研时指出，习近平主席对加强新形势下我军武器装备建设作出一系列决策指示，为国防科技创]]></CONTENT><AUTHOR><![CDATA[安普忠、倪大伟]]></AUTHOR><URL><![CDATA[http://www.mod.gov.cn/auth/2015-06/23/content_4591171.htm]]></URL><SOURCE><![CDATA[解放军报]]></SOURCE><CLASS1><![CDATA[权威发布]]></CLASS1><CLASS2><![CDATA[重要信息]]></CLASS2><KEYWORD><![CDATA[]]></KEYWORD><IMAGE><![CDATA[]]></IMAGE><DOCTYPE><![CDATA[1]]></DOCTYPE><LANGUAGES><![CDATA[1]]></LANGUAGES><SITENAME><![CDATA[国防部中文版]]></SITENAME><MASTER><![CDATA[0]]></MASTER><TRSID><![CDATA[057B525CB.00006F87.6509]]></TRSID><INPUTTIME><![CDATA[2015.6.23.]]></INPUTTIME><PUBLISHTIME><![CDATA[2015.6.23]]></PUBLISHTIME><RELEVANCE><![CDATA[0.0]]></RELEVANCE></RESULT><RESULT><TITLE><![CDATA[坚持质量至上质量强装 推进<font color=rEd>装备建设</font>创新发展
]]></TITLE><CONTENT><![CDATA[]]></CONTENT><AUTHOR><![CDATA[]]></AUTHOR><URL><![CDATA[http://news.mod.gov.cn/headlines/2015-05/15/content_4585125.htm]]></URL><SOURCE><![CDATA[]]></SOURCE><CLASS1><![CDATA[今日要闻]]></CLASS1><CLASS2><![CDATA[头条]]></CLASS2><KEYWORD><![CDATA[]]></KEYWORD><IMAGE><![CDATA[]]></IMAGE><DOCTYPE><![CDATA[1]]></DOCTYPE><LANGUAGES><![CDATA[1]]></LANGUAGES><SITENAME><![CDATA[国防部中文版]]></SITENAME><MASTER><![CDATA[0]]></MASTER><TRSID><![CDATA[057B525CB.00006DD9.BE62]]></TRSID><INPUTTIME><![CDATA[2015.6.22.]]></INPUTTIME><PUBLISHTIME><![CDATA[2015.6.22]]></PUBLISHTIME><RELEVANCE><![CDATA[0.0]]></RELEVANCE></RESULT><RESULT><TITLE><![CDATA[许其亮在江苏上海安徽等地调研<font color=rEd>装备建设</font>发展状况
]]></TITLE><CONTENT><![CDATA[&nbsp;&nbsp;&nbsp;&nbsp;&nbsp;&nbsp;&nbsp;&nbsp;中共中央政治局委员、中央军委副主席许其亮近日在江苏、上海、安徽等地调研时指出，习近平主席对加强新形势下我军武器装备建设作出一系列决策指示，为国防科技创新发展提供了战略指导。我们要坚决贯彻习主席]]></CONTENT><AUTHOR><![CDATA[记者安普忠、倪大伟]]></AUTHOR><URL><![CDATA[http://news.mod.gov.cn/headlines/2015-06/22/content_4591141.htm]]></URL><SOURCE><![CDATA[国防部网]]></SOURCE><CLASS1><![CDATA[今日要闻]]></CLASS1><CLASS2><![CDATA[头条]]></CLASS2><KEYWORD><![CDATA[许其亮,中央军委副主席,习近平,军民融合]]></KEYWORD><IMAGE><![CDATA[http://img.mod.gov.cn/news/attachement/jpg/site21/20150622/4437e658885f16f248da02.jpg]]></IMAGE><DOCTYPE><![CDATA[2]]></DOCTYPE><LANGUAGES><![CDATA[1]]></LANGUAGES><SITENAME><![CDATA[国防部中文版]]></SITENAME><MASTER><![CDATA[0]]></MASTER><TRSID><![CDATA[057B525CB.00006DD8.984D]]></TRSID><INPUTTIME><![CDATA[2015.6.22.]]></INPUTTIME><PUBLISHTIME><![CDATA[2015.6.22]]></PUBLISHTIME><RELEVANCE><![CDATA[0.0]]></RELEVANCE></RESULT><RESULT><TITLE><![CDATA[坚决贯彻习主席的<font color=rEd>装备建设</font>思想大力推进国防科技创新发展
]]></TITLE><CONTENT><![CDATA[&nbsp;&nbsp;&nbsp;&nbsp;&nbsp;&nbsp;&nbsp;&nbsp;中共中央政治局委员、中央军委副主席许其亮近日在江苏、上海、安徽等地调研时指出，习近平主席对加强新形势下我军武器装备建设作出一系列决策指示，为国防科技创新发展提供了战略指导。我们要坚决贯彻习主席]]></CONTENT><AUTHOR><![CDATA[记者安普忠、倪大伟]]></AUTHOR><URL><![CDATA[http://news.mod.gov.cn/headlines/2015-06/22/content_4591135.htm]]></URL><SOURCE><![CDATA[国防部网]]></SOURCE><CLASS1><![CDATA[今日要闻]]></CLASS1><CLASS2><![CDATA[2016年改版前国防部网站]]></CLASS2><KEYWORD><![CDATA[许其亮,中央军委副主席,习近平,军民融合]]></KEYWORD><IMAGE><![CDATA[]]></IMAGE><DOCTYPE><![CDATA[1]]></DOCTYPE><LANGUAGES><![CDATA[1]]></LANGUAGES><SITENAME><![CDATA[国防部中文版]]></SITENAME><MASTER><![CDATA[0]]></MASTER><TRSID><![CDATA[057B525CB.00006F81.A36A]]></TRSID><INPUTTIME><![CDATA[2015.6.22.]]></INPUTTIME><PUBLISHTIME><![CDATA[2015.6.22]]></PUBLISHTIME><RELEVANCE><![CDATA[0.0]]></RELEVANCE></RESULT><RESULT><TITLE><![CDATA[在实现中国梦强军梦征程中谱写我军武器<font color=rEd>装备建设</font>发展新篇章
]]></TITLE><CONTENT><![CDATA[&nbsp;&nbsp;&nbsp;&nbsp;&nbsp;&nbsp;&nbsp;&nbsp;这次全军装备工作会议，是在推进武器装备建设跨越发展的关键时期召开的一次重要会议。习主席出席会议并发表重要讲话，深刻阐明了武器装备建设带根本性方向性全局性的重大问题，为我们更好地筹划和推进武器装]]></CONTENT><AUTHOR><![CDATA[本报评论员]]></AUTHOR><URL><![CDATA[http://news.mod.gov.cn/headlines/2014-12/05/content_4555610.htm]]></URL><SOURCE><![CDATA[解放军报]]></SOURCE><CLASS1><![CDATA[今日要闻]]></CLASS1><CLASS2><![CDATA[2016年改版前国防部网站]]></CLASS2><KEYWORD><![CDATA[]]></KEYWORD><IMAGE><![CDATA[]]></IMAGE><DOCTYPE><![CDATA[1]]></DOCTYPE><LANGUAGES><![CDATA[1]]></LANGUAGES><SITENAME><![CDATA[国防部中文版]]></SITENAME><MASTER><![CDATA[0]]></MASTER><TRSID><![CDATA[057B52441.00003E99.0534]]></TRSID><INPUTTIME><![CDATA[2014.12.5.]]></INPUTTIME><PUBLISHTIME><![CDATA[2014.12.5]]></PUBLISHTIME><RELEVANCE><![CDATA[0.0]]></RELEVANCE></RESULT><RESULT><TITLE><![CDATA[简化军品市场准入程序 助力<font color=rEd>装备建设</font>“民参军”
]]></TITLE><CONTENT><![CDATA[12项举措助力装备建设“民参军” 
简化军品市场准入程序　建立采购信息交互机制 
&nbsp;&nbsp;&nbsp;&nbsp;&nbsp;&nbsp;&nbsp;&nbsp;解放军报讯 （记者邹维荣、特约记者宗兆盾）记者6月3日从正在北京举办的首届“民营企业高科技成果展览”上获悉，总装备部将会]]></CONTENT><AUTHOR><![CDATA[记者邹维荣、特约记者宗兆盾]]></AUTHOR><URL><![CDATA[http://news.mod.gov.cn/pla/2014-06/08/content_4514697.htm]]></URL><SOURCE><![CDATA[解放军报]]></SOURCE><CLASS1><![CDATA[解放军]]></CLASS1><CLASS2><![CDATA[2016年改版前国防部网站]]></CLASS2><KEYWORD><![CDATA[]]></KEYWORD><IMAGE><![CDATA[]]></IMAGE><DOCTYPE><![CDATA[1]]></DOCTYPE><LANGUAGES><![CDATA[1]]></LANGUAGES><SITENAME><![CDATA[国防部中文版]]></SITENAME><MASTER><![CDATA[0]]></MASTER><TRSID><![CDATA[057B52EA2.000156F2.4736]]></TRSID><INPUTTIME><![CDATA[2014.6.8.]]></INPUTTIME><PUBLISHTIME><![CDATA[2014.6.8]]></PUBLISHTIME><RELEVANCE><![CDATA[0.0]]></RELEVANCE></RESULT><RESULT><TITLE><![CDATA[加强预备役部队应急<font color=rEd>装备建设</font>
]]></TITLE><CONTENT><![CDATA[　　当前，预备役部队在加强核心能力建设的同时，突出了抢险救灾、反恐维稳等应急能力建设，成为活跃在各种应急救援现场的一支重要力量。而提升应急行动能力，其重要措施就是加强应急装备建设。
　　巧妇难为无米之炊]]></CONTENT><AUTHOR><![CDATA[鲁世联　张国庆]]></AUTHOR><URL><![CDATA[http://news.mod.gov.cn/reserve/2014-01/08/content_4482954.htm]]></URL><SOURCE><![CDATA[中国国防报]]></SOURCE><CLASS1><![CDATA[预备役]]></CLASS1><CLASS2><![CDATA[观点评论]]></CLASS2><KEYWORD><![CDATA[预备役,应急装备]]></KEYWORD><IMAGE><![CDATA[]]></IMAGE><DOCTYPE><![CDATA[1]]></DOCTYPE><LANGUAGES><![CDATA[1]]></LANGUAGES><SITENAME><![CDATA[国防部中文版]]></SITENAME><MASTER><![CDATA[0]]></MASTER><TRSID><![CDATA[057B52BC8.00010202.3A17]]></TRSID><INPUTTIME><![CDATA[2014.1.8.]]></INPUTTIME><PUBLISHTIME><![CDATA[2014.1.8]]></PUBLISHTIME><RELEVANCE><![CDATA[0.0]]></RELEVANCE></RESULT><NODESEARCHNAMEROOT><CLASSRES><CLASSVALUE><![CDATA[全部]]></CLASSVALUE><CLASSNUM><![CDATA[16]]></CLASSNUM></CLASSRES><CLASSRES><CLASSVALUE><![CDATA[今日要闻]]></CLASSVALUE><CLASSNUM><![CDATA[3]]></CLASSNUM></CLASSRES><CLASSRES><CLASSVALUE><![CDATA[武器装备]]></CLASSVALUE><CLASSNUM><![CDATA[1]]></CLASSNUM></CLASSRES><CLASSRES><CLASSVALUE><![CDATA[视频]]></CLASSVALUE><CLASSNUM><![CDATA[1]]></CLASSNUM></CLASSRES><CLASSRES><CLASSVALUE><![CDATA[解放军]]></CLASSVALUE><CLASSNUM><![CDATA[1]]></CLASSNUM></CLASSRES><CLASSRES><CLASSVALUE><![CDATA[民兵]]></CLASSVALUE><CLASSNUM><![CDATA[1]]></CLASSNUM></CLASSRES><CLASSRES><CLASSVALUE><![CDATA[国防建设]]></CLASSVALUE><CLASSNUM><![CDATA[1]]></CLASSNUM></CLASSRES><CLASSRES><CLASSVALUE><![CDATA[媒体报道]]></CLASSVALUE><CLASSNUM><![CDATA[1]]></CLASSNUM></CLASSRES></NODESEARCHNAMEROOT><CURPAGE><![CDATA[1]]></CURPAGE><PAGES><![CDATA[1]]></PAGES><PAGECOUNT><![CDATA[9999]]></PAGECOUNT><TOTALCOUNT><![CDATA[16]]></TOTALCOUNT><SEARCHTIME><![CDATA[42]]></SEARCHTIME></MILSEARCH>

